foxmetrics/__init__.py
foxmetrics/averagemeter.py
foxmetrics/meter_interface.py
foxmetrics/metric.py
foxmetrics/pprint.py
foxmetrics/storage_interface.py
foxmetrics/utils.py
foxmetrics-1.1.5.dist-info/METADATA
foxmetrics-1.1.5.dist-info/WHEEL
foxmetrics-1.1.5.dist-info/top_level.txt
foxmetrics-1.1.5.dist-info/RECORD
